esdb/__init__.py
esdb/client.py
esdb/exceptions.py
esdb/generated/__init__.py
esdb/generated/cluster_pb2.py
esdb/generated/cluster_pb2.pyi
esdb/generated/cluster_pb2_grpc.py
esdb/generated/code_pb2.py
esdb/generated/code_pb2.pyi
esdb/generated/code_pb2_grpc.py
esdb/generated/gossip_pb2.py
esdb/generated/gossip_pb2.pyi
esdb/generated/gossip_pb2_grpc.py
esdb/generated/monitoring_pb2.py
esdb/generated/monitoring_pb2.pyi
esdb/generated/monitoring_pb2_grpc.py
esdb/generated/operations_pb2.py
esdb/generated/operations_pb2.pyi
esdb/generated/operations_pb2_grpc.py
esdb/generated/persistent_pb2.py
esdb/generated/persistent_pb2.pyi
esdb/generated/persistent_pb2_grpc.py
esdb/generated/projections_pb2.py
esdb/generated/projections_pb2.pyi
esdb/generated/projections_pb2_grpc.py
esdb/generated/serverfeatures_pb2.py
esdb/generated/serverfeatures_pb2.pyi
esdb/generated/serverfeatures_pb2_grpc.py
esdb/generated/shared_pb2.py
esdb/generated/shared_pb2.pyi
esdb/generated/shared_pb2_grpc.py
esdb/generated/status_pb2.py
esdb/generated/status_pb2.pyi
esdb/generated/status_pb2_grpc.py
esdb/generated/streams_pb2.py
esdb/generated/streams_pb2.pyi
esdb/generated/streams_pb2_grpc.py
esdb/generated/users_pb2.py
esdb/generated/users_pb2.pyi
esdb/generated/users_pb2_grpc.py
esdb/gossip.py
esdb/py.typed
esdb/shared.py
esdb/streams/__init__.py
esdb/streams/streams.py
esdb/streams/types.py
esdb/subscriptions/__init__.py
esdb/subscriptions/subscriptions.py
esdb/subscriptions/types.py
esdb-0.3.5.dist-info/LICENSE
esdb-0.3.5.dist-info/METADATA
esdb-0.3.5.dist-info/WHEEL
esdb-0.3.5.dist-info/RECORD
