Metadata-Version: 2.1
Name: esdb
Version: 0.3.5
Summary: gRPC client for EventStore DB
Home-page: https://github.com/andriykohut/esdb-py
License: MIT
Keywords: eventstore,esdb,event sourcing,cqrs,event-sourcing,grpcio,grpc
Author: Andrii Kohut
Author-email: kogut.andriy@gmail.com
Requires-Python: >=3.9,<4.0
Classifier: License :: OSI Approved :: MIT License
Classifier: Programming Language :: Python :: 3
Classifier: Programming Language :: Python :: 3.9
Classifier: Programming Language :: Python :: 3.10
Classifier: Programming Language :: Python :: 3.11
Requires-Dist: grpcio (>=1.4.0)
Requires-Dist: protobuf (>=4.0)
Project-URL: Repository, https://github.com/andriykohut/esdb-py
